boke/__init__.py
boke/db.py
boke/generate.py
boke/gui.py
boke/main.py
boke/model.py
boke/stmt.py
boke/util.py
boke-0.0.1.dist-info/entry_points.txt
boke-0.0.1.dist-info/LICENSE
boke-0.0.1.dist-info/WHEEL
boke-0.0.1.dist-info/METADATA
boke-0.0.1.dist-info/RECORD
